Algorithmia/CLI.py
Algorithmia/__init__.py
Algorithmia/__main__.py
Algorithmia/acl.py
Algorithmia/algo_response.py
Algorithmia/algorithm.py
Algorithmia/async_response.py
Algorithmia/client.py
Algorithmia/data.py
Algorithmia/datadirectory.py
Algorithmia/datafile.py
Algorithmia/errors.py
Algorithmia/handler.py
Algorithmia/insights.py
Algorithmia/util.py
algorithmia-2.0.5.dist-info/LICENSE
algorithmia-2.0.5.dist-info/METADATA
algorithmia-2.0.5.dist-info/WHEEL
algorithmia-2.0.5.dist-info/entry_points.txt
algorithmia-2.0.5.dist-info/top_level.txt
algorithmia-2.0.5.dist-info/RECORD
